[{
  "team": "Patriots",
  "wins": 0,
  "ties": 0,
  "losses": 0
}, {
  "team": "Bills",
  "wins": 0,
  "ties": 0,
  "losses": 0
}, {
  "team": "Dolphins",
  "wins": 0,
  "ties": 0,
  "losses": 0
}, {
  "team": "Jets",
  "wins": 0,
  "ties": 0,
  "losses": 0
}, {
  "team": "Bengals",
  "wins": 0,
  "ties": 0,
  "losses": 0
}, {
  "team": "Ravens",
  "wins": 0,
  "ties": 0,
  "losses": 0
}, {
  "team": "Browns",
  "wins": 0,
  "ties": 0,
  "losses": 0
}, {
  "team": "Steelers",
  "wins": 0,

  "ties": 0,
  "losses": 0
}, {
  "team": "Colts",
  "wins": 0,
  "ties": 0,
  "losses": 0
}, {
  "team": "Texans",
  "wins": 0,
  "ties": 0,
  "losses": 0
}, {
  "team": "Titans",
  "wins": 0,
  "ties": 0,
  "losses": 0
}, {
  "team": "Jaguars",
  "wins": 0,
  "ties": 0,
  "losses": 0
}, {
  "team": "Chargers",
  "wins": 0,
  "ties": 0,
  "losses": 0
}, {
  "team": "Broncos",
  "wins": 0,
  "ties": 0,
  "losses": 0
}, {
  "team": "Chiefs",
  "wins": 0,
  "ties": 0,
  "losses": 0
}, {
  "team": "Raiders",
  "wins": 0,
  "ties": 0,
  "losses": 0
}, {
  "team": "Eagles",
  "wins": 0,
  "ties": 0,
  "losses": 0
}, {
  "team": "Cowboys",
  "wins": 0,
  "ties": 0,
  "losses": 0
}, {
  "team": "Giants",
  "wins": 0,
  "ties": 0,
  "losses": 0
}, {
  "team": "Redskins",
  "wins": 0,
  "ties": 0,
  "losses": 0
}, {
  "team": "Lions",
  "wins": 0,
  "ties": 0,
  "losses": 0
}, {
  "team": "Packers",
  "wins": 0,
  "ties": 0,
  "losses": 0
}, {
  "team": "Bears",
  "wins": 0,
  "ties": 0,
  "losses": 0
}, {
  "team": "Vikings",
  "wins": 0,
  "ties": 0,
  "losses": 0
}, {
  "team": "Panthers",
  "wins": 0,
  "ties": 0,
  "losses": 0
}, {
  "team": "Saints",
  "wins": 0,
  "ties": 0,
  "losses": 0
}, {
  "team": "Falcons",
  "wins": 0,
  "ties": 0,
  "losses": 0
}, {
  "team": "Buccaneers",
  "wins": 0,
  "ties": 0,
  "losses": 0
}, {
  "team": "Cardinals",
  "wins": 0,
  "ties": 0,
  "losses": 0
}, {
  "team": "49ers",
  "wins": 0,
  "ties": 0,
  "losses": 0
}, {
  "team": "Seahawks",
  "wins": 0,
  "ties": 0,
  "losses": 0
}, {
  "team": "Rams",
  "wins": 0,
  "ties": 0,
  "losses": 0
}]
