[{"team":"Patriots","wins":5,"ties":0,"losses":2},
{"team":"Bills","wins":3,"ties":2,"losses":1},
{"team":"Dolphins","wins":5,"ties":0,"losses":2},
{"team":"Jets","wins":5,"ties":0,"losses":2},
{"team":"Bengals","wins":5,"ties":0,"losses":2},
{"team":"Ravens","wins":5,"ties":0,"losses":2},
{"team":"Browns","wins":5,"ties":0,"losses":2},
{"team":"Steelers","wins":5,"ties":0,"losses":2},
{"team":"Colts","wins":5,"ties":0,"losses":2},
{"team":"Texans","wins":5,"ties":0,"losses":2},
{"team":"Titans","wins":5,"ties":0,"losses":2},
{"team":"Jaguars","wins":5,"ties":0,"losses":2},
{"team":"Chargers","wins":5,"ties":0,"losses":2},
{"team":"Broncos","wins":5,"ties":0,"losses":2},
{"team":"Chiefs","wins":5,"ties":0,"losses":2},
{"team":"Raiders","wins":5,"ties":0,"losses":2},
{"team":"Eagles","wins":5,"ties":0,"losses":2},
{"team":"Cowboys","wins":5,"ties":0,"losses":2},
{"team":"Giants","wins":5,"ties":0,"losses":2},
{"team":"Redskins","wins":5,"ties":0,"losses":2},
{"team":"Lions","wins":5,"ties":0,"losses":2},
{"team":"Packers","wins":5,"ties":0,"losses":2},
{"team":"Bears","wins":5,"ties":0,"losses":2},
{"team":"Vikings","wins":5,"ties":0,"losses":2},
{"team":"Panthers","wins":5,"ties":0,"losses":2},
{"team":"Saints","wins":5,"ties":0,"losses":2},
{"team":"Falcons","wins":5,"ties":0,"losses":2},
{"team":"Buccaneers","wins":5,"ties":0,"losses":2},
{"team":"Cardinals","wins":5,"ties":0,"losses":2},
{"team":"49ers","wins":5,"ties":0,"losses":2},
{"team":"Seahawks","wins":5,"ties":0,"losses":2},
{"team":"Rams","wins":5,"ties":0,"losses":2}]
